{"name":"Heresy","tagline":"A BASIC-flavored Lisp dialect","body":"Heresy\r\n======\r\n\r\nHeresy is a BASIC-inspired functional dialect of Lisp, currently implemented as a Racket language that can be loaded by ``#lang s-exp``.\r\n\r\nHeresy aims to provide a simple, semi-pure functional Lisp language that is nevertheless familiar to programmers of BASIC, by providing a combination of familiar control structures and features with purely functional execution.\r\n\r\nThe code Copyright 2014 by John S. Berry III, and is licensed via the LGPL v3.\r\n\r\nInstallation\r\n------------\r\n\r\nTo install:\r\n\r\n``raco pkg install git://github.com/jarcane/heresy``\r\n\r\nTo use, append this to the start of your file in DrRacket or your favorite text-editor:\r\n\r\n``#lang s-exp heresy``\r\n","google":"","note":"Don't delete this file! It's used internally to help with page regeneration."}